MANIFEST.in
README.rst
distribute_setup.py
setup.py
bin/cnd
bin/cndcc
cnd/__init__.py
cnd/version.py
cnd.egg-info/PKG-INFO
cnd.egg-info/SOURCES.txt
cnd.egg-info/dependency_links.txt
cnd.egg-info/not-zip-safe
cnd.egg-info/requires.txt
cnd.egg-info/top_level.txt
examples/allheaders.c
examples/basic.c
examples/creal.c
examples/parser-stress.c
ply-shipped/README
ply-shipped/ply/__init__.py
ply-shipped/ply/cpp.py
ply-shipped/ply/ctokens.py
ply-shipped/ply/lex.py
ply-shipped/ply/yacc.py
pycparser-shipped/LICENSE
pycparser-shipped/README.html
pycparser-shipped/pycparser/__init__.py
pycparser-shipped/pycparser/_ast_gen.py
pycparser-shipped/pycparser/_build_tables.py
pycparser-shipped/pycparser/ast_transforms.py
pycparser-shipped/pycparser/c_ast.py
pycparser-shipped/pycparser/c_generator.py
pycparser-shipped/pycparser/c_lexer.py
pycparser-shipped/pycparser/c_parser.py
pycparser-shipped/pycparser/plyparser.py
pycparserext-shipped/pycparserext/__init__.py
pycparserext-shipped/pycparserext/c_generator.py
pycparserext-shipped/pycparserext/ext_c_generator.py
pycparserext-shipped/pycparserext/ext_c_lexer.py
pycparserext-shipped/pycparserext/ext_c_parser.py