Metadata-Version: 1.0
Name: cnd
Version: 2012.1
Summary: A preprocessor that gives C multidimensional arrays
Home-page: http://mathema.tician.de/software/cnd
Author: Andreas Kloeckner
Author-email: inform@tiker.net
License: MIT
Platform: UNKNOWN
